activation_model_mixin/__init__.py
activation_model_mixin/admin.py
activation_model_mixin/apps.py
activation_model_mixin/managers.py
activation_model_mixin/models.py
activation_model_mixin/querysets.py
activation_model_mixin/signals.py
activation_model_mixin/static/css/activation_model_mixin.css
activation_model_mixin/static/js/activation_model_mixin.js
activation_model_mixin/templates/admin/activation/activation_change_form.html
activation_model_mixin/templates/admin/activation/submit_line.html
activation_model_mixin/templatetags/__init__.py
activation_model_mixin/templatetags/activation_admin.py
django_activation_model_mixin-0.1.0.dist-info/LICENSE.md
django_activation_model_mixin-0.1.0.dist-info/METADATA
django_activation_model_mixin-0.1.0.dist-info/WHEEL
django_activation_model_mixin-0.1.0.dist-info/top_level.txt
django_activation_model_mixin-0.1.0.dist-info/RECORD
